pytelebirr
