Metadata-Version: 2.1
Name: pytelebirr
Version: 0.2.3
Summary: Telebirr with python 
Home-page: https://github.com/telebirrapi/pytelebirr
Author: wizkiye
Author-email: wizkiye@gmail.com
License: MIT License
Platform: UNKNOWN
Classifier: Development Status :: 3 - Alpha
Classifier: Intended Audience :: Developers
Classifier: Topic :: Software Development :: Build Tools
Classifier: License :: OSI Approved :: MIT License
Classifier: Programming Language :: Python :: 3
Classifier: Programming Language :: Python :: 3.8
Requires-Python: >=3.8
